pyproject2conda/__init__.py
pyproject2conda/__main__.py
pyproject2conda/_compat.py
pyproject2conda/_typing.py
pyproject2conda/_typing_compat.py
pyproject2conda/cli.py
pyproject2conda/config.py
pyproject2conda/overrides.py
pyproject2conda/py.typed
pyproject2conda/requirements.py
pyproject2conda/utils.py
pyproject2conda-0.22.1.dist-info/METADATA
pyproject2conda-0.22.1.dist-info/WHEEL
pyproject2conda-0.22.1.dist-info/entry_points.txt
pyproject2conda-0.22.1.dist-info/licenses/LICENSE
pyproject2conda-0.22.1.dist-info/RECORD
