Metadata-Version: 2.4
Name: pyproject2conda
Version: 0.22.1
Summary: A script to convert a Python project declared on a pyproject.toml to a conda environment.
Project-URL: Documentation, https://pages.nist.gov/pyproject2conda/
Project-URL: Homepage, https://github.com/usnistgov/pyproject2conda
Author-email: "William P. Krekelberg" <wpk@nist.gov>
License-Expression: NIST-PD
License-File: LICENSE
Keywords: pyproject2conda
Classifier: Development Status :: 2 - Pre-Alpha
Classifier: Intended Audience :: Science/Research
Classifier: Operating System :: OS Independent
Classifier: Programming Language :: Python
Classifier: Programming Language :: Python :: 3 :: Only
Classifier: Programming Language :: Python :: 3.10
Classifier: Programming Language :: Python :: 3.11
Classifier: Programming Language :: Python :: 3.12
Classifier: Programming Language :: Python :: 3.13
Classifier: Topic :: Scientific/Engineering
Requires-Python: >=3.10
Requires-Dist: dependency-groups
Requires-Dist: packaging
Requires-Dist: tomli; python_version < '3.11'
Requires-Dist: typer
Requires-Dist: typing-extensions; python_version < '3.11'
